holophonor-0.1.0.dist-info/METADATA
holophonor-0.1.0.dist-info/WHEEL
holophonor-0.1.0.dist-info/entry_points.txt
holophonor/__init__.py
holophonor/_version.py
holophonor/constants.py
holophonor/daw.py
holophonor/freewheeling.py
holophonor/holospecs.py
holophonor/launchpadMK2.py
holophonor/launchpadS.py
holophonor/launchpadX.py
holophonor/main.py
holophonor/qsynth.py
holophonor-0.1.0.dist-info/RECORD
