Metadata-Version: 2.1
Name: holophonor
Version: 0.1.0
Summary: Live looping, unlimited!
Author-Email: Quaternion Media <holophonor@quaternion.media>
License: MIT
Requires-Python: <4,>=3.8.1
Requires-Dist: pluggy<1.1,>=1.0.0
Requires-Dist: python-rtmidi<1.5,>=1.4.9
Requires-Dist: loguru>=0.6.0
